{
  "subject": "第二届天使动漫“萌王之王”萌战——天使之羽翼战决赛",
  "postlist": [
    {
      "pid": "75022668",
      "author": "pwu",
      "authorid": "2164964",
      "avatar": "https://tu.ts-dm.net/imgs/2022/06/817049b072fce189.gif",
      "authortitle": "<font color=\"blue\">梦幻天使</font>",
      "authorgid": "31",
      "author_nickname": "pwu",
      "timestamp": "1741238944",
      "subject": "",
      "message": "惠惠@为美好的世界献上祝福！ <br /><strong><font color=\"White\"><font style=\"background-color:Orange\">爱蜜莉雅@Re:从零开始的异世界生活 2nd season(后半)</font></font></strong> <br />木之本樱@魔卡少女樱 透明牌篇 <br /><strong><font color=\"White\"><font style=\"background-color:Orange\">喜多川海梦@更衣人偶坠入爱河</font></font></strong> <br /><strong><font color=\"White\"><font style=\"background-color:Orange\">和泉纱雾@情色漫画老师</font></font></strong> <br />芙莉莲@葬送的芙莉莲 <br />康娜@小林家的妹抖龙 <br />阿尼亚·福杰@间谍过家家(前半) <br />",
      "first": "0",
      "floor": 151,
      "platform": 0
    },
    {
      "pid": "75023554",
      "author": "kira超绝可爱",
      "authorid": "1946428",
      "avatar": "http://i.ibb.co/XzQtX9s/image.jpg",
      "authortitle": "水天使",
      "authorgid": "12",
      "author_nickname": "kira",
      "timestamp": "1741254642",
      "subject": "",
      "message": "惠惠@为美好的世界献上祝福！ <br />爱蜜莉雅@Re:从零开始的异世界生活 2nd season(后半) <br /><strong><font color=\"White\"><font style=\"background-color:Orange\">木之本樱@魔卡少女樱 透明牌篇</font></font></strong> <br /><strong><font color=\"White\"><font style=\"background-color:Orange\">喜多川海梦@更衣人偶坠入爱河</font></font></strong> <br />和泉纱雾@情色漫画老师 <br />芙莉莲@葬送的芙莉莲 <br />康娜@小林家的妹抖龙 <br />阿尼亚·福杰@间谍过家家(前半) <br />",
      "first": "0",
      "floor": 152,
      "platform": 0
    },
    {
      "pid": "75025654",
      "author": "TR83",
      "authorid": "2074148",
      "avatar": "https://www.z4a.net/images/2024/09/18/T.gif",
      "authortitle": "<font color=\"Red\">区版主</font>",
      "authorgid": "79",
      "author_nickname": "",
      "timestamp": "1741274334",
      "subject": "",
      "message": "惠惠@为美好的世界献上祝福！ <br />爱蜜莉雅@Re:从零开始的异世界生活 2nd season(后半) <br /><strong><font color=\"White\"><font style=\"background-color:Orange\">木之本樱@魔卡少女樱 透明牌篇</font></font></strong> <br />喜多川海梦@更衣人偶坠入爱河 <br />和泉纱雾@情色漫画老师 <br />芙莉莲@葬送的芙莉莲 <br /><strong><font color=\"White\"><font style=\"background-color:Orange\">康娜@小林家的妹抖龙</font></font></strong> <br /><strong><font color=\"White\"><font style=\"background-color:Orange\">阿尼亚·福杰@间谍过家家(前半)</font></font></strong> <br />",
      "first": "0",
      "floor": 153,
      "platform": 0
    },
    {
      "pid": "75027780",
      "author": "eve556613339",
      "authorid": "1033390",
      "avatar": "https://www.tsdm39.com/uc_server/data/avatar/001/03/33/90_avatar_middle.jpg",
      "authortitle": "曙光天使",
      "authorgid": "61",
      "author_nickname": "怪物",
      "timestamp": "1741301369",
      "subject": "",
      "message": "惠惠@为美好的世界献上祝福！ <br /><strong><font color=\"White\"><font style=\"background-color:Orange\">爱蜜莉雅@Re:从零开始的异世界生活 2nd season(后半)</font></font></strong> <br />木之本樱@魔卡少女樱 透明牌篇 <br /><strong><font color=\"White\"><font style=\"background-color:Orange\">喜多川海梦@更衣人偶坠入爱河</font></font></strong> <br />和泉纱雾@情色漫画老师 <br />芙莉莲@葬送的芙莉莲 <br />康娜@小林家的妹抖龙 <br />阿尼亚·福杰@间谍过家家(前半) <br />",
      "first": "0",
      "floor": 154,
      "platform": 0
    },
    {
      "pid": "75028786",
      "author": "栀子花不开",
      "authorid": "1980835",
      "avatar": "https://tu.ts-dm.net/imgs/2022/06/a1f50a071e8c3f43.gif",
      "authortitle": "片翼天使LV.2",
      "authorgid": "72",
      "author_nickname": "栀子花不开",
      "timestamp": "1741308760",
      "subject": "",
      "message": "惠惠@为美好的世界献上祝福！ <br />爱蜜莉雅@Re:从零开始的异世界生活 2nd season(后半) <br /><strong><font color=\"White\"><font style=\"background-color:Orange\">木之本樱@魔卡少女樱 透明牌篇</font></font></strong> <br />喜多川海梦@更衣人偶坠入爱河 <br />和泉纱雾@情色漫画老师 <br />芙莉莲@葬送的芙莉莲 <br />康娜@小林家的妹抖龙 <br />阿尼亚·福杰@间谍过家家(前半) <br />",
      "first": "0",
      "floor": 155,
      "platform": 0
    },
    {
      "pid": "75034688",
      "author": "最爱汝嫣的我",
      "authorid": "1946429",
      "avatar": "http://i.ibb.co/ZW7z6Rx/58264e36acaf2edd3dc2e253841001e93901930c.png",
      "authortitle": "水天使",
      "authorgid": "12",
      "author_nickname": "嫣儿",
      "timestamp": "1741361723",
      "subject": "",
      "message": "惠惠@为美好的世界献上祝福！ <br />爱蜜莉雅@Re:从零开始的异世界生活 2nd season(后半) <br /><strong><font color=\"White\"><font style=\"background-color:Orange\">木之本樱@魔卡少女樱 透明牌篇</font></font></strong> <br /><strong><font color=\"White\"><font style=\"background-color:Orange\">喜多川海梦@更衣人偶坠入爱河</font></font></strong> <br />和泉纱雾@情色漫画老师 <br />芙莉莲@葬送的芙莉莲 <br />康娜@小林家的妹抖龙 <br />阿尼亚·福杰@间谍过家家(前半) <br />",
      "first": "0",
      "floor": 156,
      "platform": 0
    },
    {
      "pid": "75038635",
      "author": "AgnesD",
      "authorid": "1992129",
      "avatar": "http://i.ibb.co/Cvzd1qv/e87315385343fbf2ee3f2d63a77eca8065388f0a.png",
      "authortitle": "水天使",
      "authorgid": "12",
      "author_nickname": "天使",
      "timestamp": "1741395067",
      "subject": "",
      "message": "惠惠@为美好的世界献上祝福！ <br />爱蜜莉雅@Re:从零开始的异世界生活 2nd season(后半) <br /><strong><font color=\"White\"><font style=\"background-color:Orange\">木之本樱@魔卡少女樱 透明牌篇</font></font></strong> <br /><strong><font color=\"White\"><font style=\"background-color:Orange\">喜多川海梦@更衣人偶坠入爱河</font></font></strong> <br />和泉纱雾@情色漫画老师 <br />芙莉莲@葬送的芙莉莲 <br />康娜@小林家的妹抖龙 <br />阿尼亚·福杰@间谍过家家(前半) <br />",
      "first": "0",
      "floor": 157,
      "platform": 0
    },
    {
      "pid": "75038692",
      "author": "龙族之夏",
      "authorid": "1977916",
      "avatar": "https://tu.ts-dm.net/imgs/2022/06/f7db5b20b182ef7f.gif",
      "authortitle": "水天使",
      "authorgid": "12",
      "author_nickname": "龙族之夏",
      "timestamp": "1741395520",
      "subject": "",
      "message": "惠惠@为美好的世界献上祝福！ <br />爱蜜莉雅@Re:从零开始的异世界生活 2nd season(后半) <br /><strong><font color=\"White\"><font style=\"background-color:Orange\">木之本樱@魔卡少女樱 透明牌篇</font></font></strong> <br /><strong><font color=\"White\"><font style=\"background-color:Orange\">喜多川海梦@更衣人偶坠入爱河</font></font></strong> <br /><strong><font color=\"White\"><font style=\"background-color:Orange\">和泉纱雾@情色漫画老师</font></font></strong> <br />芙莉莲@葬送的芙莉莲 <br />康娜@小林家的妹抖龙 <br />阿尼亚·福杰@间谍过家家(前半) <br />",
      "first": "0",
      "floor": 158,
      "platform": 0
    },
    {
      "pid": "75039018",
      "author": "hakozaki",
      "authorid": "1705726",
      "avatar": "http://pic.yupoo.com/laevateinn/f5e9cad3/5f87f711.jpg",
      "authortitle": "<font color=\"blue\">梦幻天使★</font>",
      "authorgid": "139",
      "author_nickname": "星梨花",
      "timestamp": "1741397657",
      "subject": "",
      "message": "惠惠@为美好的世界献上祝福！ <br /><strong><font color=\"White\"><font style=\"background-color:Orange\">爱蜜莉雅@Re:从零开始的异世界生活 2nd season(后半)</font></font></strong> <br />木之本樱@魔卡少女樱 透明牌篇 <br />喜多川海梦@更衣人偶坠入爱河 <br /><strong><font color=\"White\"><font style=\"background-color:Orange\">和泉纱雾@情色漫画老师</font></font></strong> <br />芙莉莲@葬送的芙莉莲 <br />康娜@小林家的妹抖龙 <br /><strong><font color=\"White\"><font style=\"background-color:Orange\">阿尼亚·福杰@间谍过家家(前半)</font></font></strong> ",
      "first": "0",
      "floor": 159,
      "platform": 0
    },
    {
      "pid": "75039032",
      "author": "山崎甜虾",
      "authorid": "1985620",
      "avatar": "http://i.ibb.co/7npYf2y/6c88dc33c895d143990aa6de7df082025baf07f9.png",
      "authortitle": "片翼天使LV.2",
      "authorgid": "72",
      "author_nickname": "",
      "timestamp": "1741397757",
      "subject": "",
      "message": "惠惠@为美好的世界献上祝福！ <br />爱蜜莉雅@Re:从零开始的异世界生活 2nd season(后半) <br /><strong><font color=\"White\"><font style=\"background-color:Orange\">木之本樱@魔卡少女樱 透明牌篇</font></font></strong> <br /><strong><font color=\"White\"><font style=\"background-color:Orange\">喜多川海梦@更衣人偶坠入爱河</font></font></strong> <br />和泉纱雾@情色漫画老师 <br />芙莉莲@葬送的芙莉莲 <br />康娜@小林家的妹抖龙 <br /><strong><font color=\"White\"><font style=\"background-color:Orange\">阿尼亚·福杰@间谍过家家(前半)</font></font></strong> <br />",
      "first": "0",
      "floor": 160,
      "platform": 0
    }
  ],
  "totalpost": "178",
  "tpp": 10,
  "fid": "418",
  "thread_author": "YQ17",
  "thread_authorid": 1202448,
  "ismoderator": 0,
  "thread_price": "0",
  "thread_paid": 1,
  "extcreditsname": {
    "4": "天然",
    "3": "宣传",
    "5": "腹黑",
    "6": "精灵",
    "7": "金蛋",
    "2": "天使币",
    "1": "威望"
  }
}