{
  "subject": "第二届天使动漫“萌王之王”萌战——天使之羽翼战决赛",
  "postlist": [
    {
      "pid": "75015190",
      "author": "花开洛溪",
      "authorid": "1978208",
      "avatar": "http://i.ibb.co/ZmQw0KS/dcfc522c11dfa9ec73ad846c75d0f703908fc1fe.png",
      "authortitle": "昼天使",
      "authorgid": "13",
      "author_nickname": "花开洛溪",
      "timestamp": "1741175266",
      "subject": "",
      "message": "惠惠@为美好的世界献上祝福！ <br />爱蜜莉雅@Re:从零开始的异世界生活 2nd season(后半) <br /><strong><font color=\"White\"><font style=\"background-color:Orange\">木之本樱@魔卡少女樱 透明牌篇</font></font></strong> <br /><strong><font color=\"White\"><font style=\"background-color:Orange\">喜多川海梦@更衣人偶坠入爱河</font></font></strong> <br /><strong><font color=\"White\"><font style=\"background-color:Orange\">和泉纱雾@情色漫画老师</font></font></strong> <br />芙莉莲@葬送的芙莉莲 <br />康娜@小林家的妹抖龙 <br />阿尼亚·福杰@间谍过家家(前半) <br />",
      "first": "0",
      "floor": 141,
      "platform": 0
    },
    {
      "pid": "75015441",
      "author": "A路人君",
      "authorid": "2051456",
      "avatar": "https://tu.ts-dm.net/imgs/2022/06/de1b3c0309a67fc5.gif",
      "authortitle": "霞天使",
      "authorgid": "15",
      "author_nickname": "",
      "timestamp": "1741177630",
      "subject": "",
      "message": "<strong><font color=\"White\"><font style=\"background-color:Orange\">惠惠@为美好的世界献上祝福！</font></font></strong> <br />爱蜜莉雅@Re:从零开始的异世界生活 2nd season(后半) <br /><strong><font color=\"White\"><font style=\"background-color:Orange\">木之本樱@魔卡少女樱 透明牌篇</font></font></strong> <br />喜多川海梦@更衣人偶坠入爱河 <br /><strong><font color=\"White\"><font style=\"background-color:Orange\">和泉纱雾@情色漫画老师</font></font></strong> <br />芙莉莲@葬送的芙莉莲 <br />康娜@小林家的妹抖龙 <br />阿尼亚·福杰@间谍过家家(前半)",
      "first": "0",
      "floor": 142,
      "platform": 0
    },
    {
      "pid": "75017593",
      "author": "sea_lantern",
      "authorid": "2107174",
      "avatar": "https://minecraft.fandom.com/wiki/Sea_Lantern?file=Sea_Lantern_JE1.gif",
      "authortitle": "<font color=\"blue\">梦幻天使</font>",
      "authorgid": "31",
      "author_nickname": "",
      "timestamp": "1741185891",
      "subject": "",
      "message": "<strong><font color=\"White\"><font style=\"background-color:Orange\">惠惠@为美好的世界献上祝福！</font></font></strong> <br />爱蜜莉雅@Re:从零开始的异世界生活 2nd season(后半) <br />木之本樱@魔卡少女樱 透明牌篇 <br />喜多川海梦@更衣人偶坠入爱河 <br />和泉纱雾@情色漫画老师 <br /><strong><font color=\"White\"><font style=\"background-color:Orange\">芙莉莲@葬送的芙莉莲</font></font></strong> <br />康娜@小林家的妹抖龙 <br /><strong><font color=\"White\"><font style=\"background-color:Orange\">阿尼亚·福杰@间谍过家家(前半)</font></font></strong> <br />",
      "first": "0",
      "floor": 143,
      "platform": 0
    },
    {
      "pid": "75017623",
      "author": "bestzoo",
      "authorid": "2198976",
      "avatar": "https://tu.ts-dm.net/imgs/2022/06/959f6057c74dc148.gif",
      "authortitle": "<font color=\"blue\">梦幻天使</font>",
      "authorgid": "31",
      "author_nickname": "空水蓝果",
      "timestamp": "1741186142",
      "subject": "",
      "message": "<strong><font color=\"White\"><font style=\"background-color:Orange\">惠惠@为美好的世界献上祝福！</font></font></strong> <br />爱蜜莉雅@Re:从零开始的异世界生活 2nd season(后半) <br />木之本樱@魔卡少女樱 透明牌篇 <br />喜多川海梦@更衣人偶坠入爱河 <br /><strong><font color=\"White\"><font style=\"background-color:Orange\">和泉纱雾@情色漫画老师</font></font></strong> <br />芙莉莲@葬送的芙莉莲 <br /><strong><font color=\"White\"><font style=\"background-color:Orange\">康娜@小林家的妹抖龙</font></font></strong> <br />阿尼亚·福杰@间谍过家家(前半) <br />",
      "first": "0",
      "floor": 144,
      "platform": 0
    },
    {
      "pid": "75017630",
      "author": "b13883659810",
      "authorid": "1934057",
      "avatar": "https://www.z4a.net/images/2020/12/13/11f288bcef86f8ca3.png",
      "authortitle": "<font color=\"blue\">梦幻天使</font>",
      "authorgid": "31",
      "author_nickname": "默世",
      "timestamp": "1741186233",
      "subject": "",
      "message": "<strong><font color=\"White\"><font style=\"background-color:Orange\">惠惠@为美好的世界献上祝福！</font></font></strong> <br /><strong><font color=\"White\"><font style=\"background-color:Orange\">爱蜜莉雅@Re:从零开始的异世界生活 2nd season(后半)</font></font></strong> <br />木之本樱@魔卡少女樱 透明牌篇 <br />喜多川海梦@更衣人偶坠入爱河 <br />和泉纱雾@情色漫画老师 <br />芙莉莲@葬送的芙莉莲 <br /><strong><font color=\"White\"><font style=\"background-color:Orange\">康娜@小林家的妹抖龙</font></font></strong> <br />阿尼亚·福杰@间谍过家家(前半) <br />",
      "first": "0",
      "floor": 145,
      "platform": 0
    },
    {
      "pid": "75017805",
      "author": "绫濑小莲雪",
      "authorid": "1985634",
      "avatar": "http://i.ibb.co/KXf986d/27d895529822720e7fcf5b0775cb0a46f31fabfd.png",
      "authortitle": "片翼天使LV.2",
      "authorgid": "72",
      "author_nickname": "",
      "timestamp": "1741187687",
      "subject": "",
      "message": "惠惠@为美好的世界献上祝福！ <br />爱蜜莉雅@Re:从零开始的异世界生活 2nd season(后半) <br /><strong><font color=\"White\"><font style=\"background-color:Orange\">木之本樱@魔卡少女樱 透明牌篇</font></font></strong> <br /><strong><font color=\"White\"><font style=\"background-color:Orange\">喜多川海梦@更衣人偶坠入爱河</font></font></strong> <br />和泉纱雾@情色漫画老师 <br />芙莉莲@葬送的芙莉莲 <br />康娜@小林家的妹抖龙 <br />阿尼亚·福杰@间谍过家家(前半) <br />",
      "first": "0",
      "floor": 146,
      "platform": 0
    },
    {
      "pid": "75018210",
      "author": "Lorry97",
      "authorid": "62852",
      "avatar": "https://i.imgur.com/AwumyiM.png",
      "authortitle": "<font color=\"blue\">梦幻天使★</font>",
      "authorgid": "139",
      "author_nickname": "潜水酋长",
      "timestamp": "1741191631",
      "subject": "",
      "message": "<strong><font color=\"White\"><font style=\"background-color:Orange\">惠惠@为美好的世界献上祝福！</font></font></strong> <br /><strong><font color=\"White\"><font style=\"background-color:Orange\">爱蜜莉雅@Re:从零开始的异世界生活 2nd season(后半)</font></font></strong> <br />木之本樱@魔卡少女樱 透明牌篇 <br />喜多川海梦@更衣人偶坠入爱河 <br /><strong><font color=\"White\"><font style=\"background-color:Orange\">和泉纱雾@情色漫画老师</font></font></strong> <br />芙莉莲@葬送的芙莉莲 <br />康娜@小林家的妹抖龙 <br />阿尼亚·福杰@间谍过家家(前半) <br />",
      "first": "0",
      "floor": 147,
      "platform": 0
    },
    {
      "pid": "75019478",
      "author": "hermione_evans",
      "authorid": "1782751",
      "avatar": "https://images2.imgbox.com/bb/02/O1jjykIX_o.jpg",
      "authortitle": "<font color=\"blue\">梦幻天使</font>",
      "authorgid": "31",
      "author_nickname": "hermione_evans",
      "timestamp": "1741205613",
      "subject": "",
      "message": "惠惠@为美好的世界献上祝福！ <br />爱蜜莉雅@Re:从零开始的异世界生活 2nd season(后半) <br /><strong><font color=\"White\"><font style=\"background-color:Orange\">木之本樱@魔卡少女樱 透明牌篇</font></font></strong> <br />喜多川海梦@更衣人偶坠入爱河 <br /><strong><font color=\"White\"><font style=\"background-color:Orange\">和泉纱雾@情色漫画老师</font></font></strong> <br /><strong><font color=\"White\"><font style=\"background-color:Orange\">芙莉莲@葬送的芙莉莲</font></font></strong> <br />康娜@小林家的妹抖龙 <br />阿尼亚·福杰@间谍过家家(前半) <br />",
      "first": "0",
      "floor": 148,
      "platform": 0
    },
    {
      "pid": "75021950",
      "author": "facekaomoon",
      "authorid": "1985636",
      "avatar": "http://i.ibb.co/3sBjpNT/9d338201a18b87d6d63379fa0c0828381e30fd96.gif",
      "authortitle": "片翼天使LV.2",
      "authorgid": "72",
      "author_nickname": "",
      "timestamp": "1741230724",
      "subject": "",
      "message": "惠惠@为美好的世界献上祝福！ <br />爱蜜莉雅@Re:从零开始的异世界生活 2nd season(后半) <br /><strong><font color=\"White\"><font style=\"background-color:Orange\">木之本樱@魔卡少女樱 透明牌篇</font></font></strong> <br />喜多川海梦@更衣人偶坠入爱河 <br />和泉纱雾@情色漫画老师 <br /><strong><font color=\"White\"><font style=\"background-color:Orange\">芙莉莲@葬送的芙莉莲</font></font></strong> <br />康娜@小林家的妹抖龙 <br /><strong><font color=\"White\"><font style=\"background-color:Orange\">阿尼亚·福杰@间谍过家家(前半)</font></font></strong> <br />",
      "first": "0",
      "floor": 149,
      "platform": 0
    },
    {
      "pid": "75021968",
      "author": "右代宫朱志香",
      "authorid": "1976931",
      "avatar": "https://tu.ts-dm.net/imgs/2022/06/1a9c78ae7613c12b.gif",
      "authortitle": "水天使",
      "authorgid": "12",
      "author_nickname": "Jessi",
      "timestamp": "1741230978",
      "subject": "",
      "message": "惠惠@为美好的世界献上祝福！ <br />爱蜜莉雅@Re:从零开始的异世界生活 2nd season(后半) <br /><strong><font color=\"White\"><font style=\"background-color:Orange\">木之本樱@魔卡少女樱 透明牌篇</font></font></strong> <br /><strong><font color=\"White\"><font style=\"background-color:Orange\">喜多川海梦@更衣人偶坠入爱河</font></font></strong> <br />和泉纱雾@情色漫画老师 <br />芙莉莲@葬送的芙莉莲 <br />康娜@小林家的妹抖龙 <br />阿尼亚·福杰@间谍过家家(前半) <br />",
      "first": "0",
      "floor": 150,
      "platform": 0
    }
  ],
  "totalpost": "178",
  "tpp": 10,
  "fid": "418",
  "thread_author": "YQ17",
  "thread_authorid": 1202448,
  "ismoderator": 0,
  "thread_price": "0",
  "thread_paid": 1,
  "extcreditsname": {
    "6": "精灵",
    "1": "威望",
    "3": "宣传",
    "2": "天使币",
    "4": "天然",
    "5": "腹黑",
    "7": "金蛋"
  }
}