{
  "avatar": "https://tu.ts-dm.net/imgs/2024/09/b8f33ad5d772babc.gif",
  "username": "miliyat001",
  "uid": "124025",
  "email_verified": true,
  "video_verified": false,
  "custom_title": "高阶",
  "signature": "<table><tbody><tr><td><a href=\"https://www.tsdm39.com/forum.php?mod=viewthread&amp;tid=1228699\" target=\"_blank\"><img src=\"https://img.ts-dm.net/images/2025/02/21/887175ec130e5afed43f6f686f735055.gif\" border=\"0\" alt=\"\"></a></td></tr></tbody></table>",
  "friends_count": "<em>统计信息</em><a href=\"home.php?mod=space&amp;uid=124025&amp;do=friend&amp;view=me&amp;from=space\" target=\"_blank\">好友数 74</a>",
  "birth_year": "",
  "birth_month": "",
  "birth_day": "",
  "zodiac": null,
  "msn": null,
  "introduction": "喜欢少女漫画",
  "nickname": null,
  "gender": "女",
  "from_where": null,
  "qq": null,
  "check_in_days_count": 4647,
  "check_in_this_month_count": "19",
  "check_in_recent_time": "2025-03-19 16:54",
  "check_in_all_coins": "33927",
  "check_in_last_time_coins": null,
  "check_in_level": "[LV.Master]伴坛终老",
  "check_in_next_level": null,
  "check_in_next_level_days": null,
  "check_in_today_status": "今天已签到",
  "moderator_group": null,
  "user_group": "永恒天使",
  "online_time": "65535 小时",
  "register_time": "2011-11-6 19:40",
  "last_visit_time": "2025-3-19 21:55",
  "last_active_time": "2025-3-19 16:53",
  "last_post_time": "2025-3-19 21:55",
  "timezone": "(GMT +08:00) 北京, 香港, 帕斯, 新加坡, 台北",
  "credits": {
    "积分": "594706",
    "宣传": "14209",
    "金蛋": "4",
    "威望": "594706",
    "腹黑": "315307",
    "天然": "315306",
    "天使币": "12456",
    "精灵": "32"
  }
}