{
  "subject": "2025天使动漫萌战 百合表演赛——初赛A组",
  "postlist": [
    {
      "pid": "75488566",
      "author": "苏浅蓝",
      "authorid": "1917231",
      "avatar": "https://s2.loli.net/2025/04/19/WdPo8sIZ9FxiQjf.png",
      "authortitle": "<font color=\"blue\">梦幻天使</font>",
      "authorgid": "31",
      "author_nickname": "苏浅蓝",
      "timestamp": "1746242927",
      "subject": "",
      "message": "北条沙都子&amp;古手梨花@寒蝉鸣泣之时 <br />大宫忍&amp;爱丽丝·卡塔雷特@HELLO!! 黄金拼图 <br />保登心爱&amp;香风智乃@请问您今天要来点兔子吗？？ <br />古宫乃乃香&amp;诺艾尔@天体的秩序 <br />南雫&amp;野田琴音@樱Trick <br />黄前久美子&amp;高坂丽奈@吹响吧！上低音号 第三季 <br />萩生响&amp;江古田莲@ANNE HAPPY♪ <br />千矢&amp;巽绀@Urara迷路帖 <br />凑友希那&amp;今井莉莎@BanG Dream! <br />天堂真矢&amp;西条克洛迪娜@少女☆歌剧 Revue Starlight <br />小糸侑&amp;七海灯子@终将成为你 <br />十仓荣依子&amp;千石冠@Slow Start <br />小邪神&amp;花园百合铃@邪神与厨二病少女 <br />安达樱&amp;岛村抱月@安达与岛村 <br />绘里飘&amp;市井舞菜@神推偶像登上武道馆我就死而无憾 <br />高咲侑&amp;上原步梦@Love Live! 虹咲学园校园偶像同好会 <br />美树沙耶香&amp;佐仓杏子@魔法少女小圆 <br />玛瑙&amp;时任灯里@处刑少女的生存之道 <br />间宫果乃子&amp;知花纯加@我的百合乃工作是也！ <br /><strong><font color=\"White\"><font style=\"background-color:Orange\">三角初华&amp;丰川祥子@BanG Dream! Ave Mujica</font></font></strong> <br />缇拉鞠・加德斯布拉德&amp;薇儿赫泽@家里蹲吸血姬的苦闷 <br />春山花奈&amp;薄赖瑞希@群花绽放，彷如修罗 <br />安洁·勒卡雷&amp;公主@公主准则 <br />谏山黄泉&amp;土宫神乐@食灵-零- <br />河合真子&amp;古馆九礼亚@时光流逝，饭菜依旧美味 <br />",
      "first": "0",
      "floor": 91,
      "platform": 0
    },
    {
      "pid": "75488649",
      "author": "桂雪雏",
      "authorid": "883520",
      "avatar": "https://images2.imgbox.com/ce/3d/1Et5DtRp_o.gif",
      "authortitle": "<font color=\"blue\">森林天使</font>",
      "authorgid": "21",
      "author_nickname": "迎新时间不固定，忙完/摸鱼时间会清提醒w",
      "timestamp": "1746243738",
      "subject": "",
      "message": "北条沙都子&amp;古手梨花@寒蝉鸣泣之时 <br />大宫忍&amp;爱丽丝·卡塔雷特@HELLO!! 黄金拼图 <br /><strong><font color=\"White\"><font style=\"background-color:Orange\">保登心爱&amp;香风智乃@请问您今天要来点兔子吗？？</font></font></strong> <br />古宫乃乃香&amp;诺艾尔@天体的秩序 <br />南雫&amp;野田琴音@樱Trick <br />黄前久美子&amp;高坂丽奈@吹响吧！上低音号 第三季 <br />萩生响&amp;江古田莲@ANNE HAPPY♪ <br />千矢&amp;巽绀@Urara迷路帖 <br />凑友希那&amp;今井莉莎@BanG Dream! <br />天堂真矢&amp;西条克洛迪娜@少女☆歌剧 Revue Starlight <br />小糸侑&amp;七海灯子@终将成为你 <br />十仓荣依子&amp;千石冠@Slow Start <br />小邪神&amp;花园百合铃@邪神与厨二病少女 <br />安达樱&amp;岛村抱月@安达与岛村 <br />绘里飘&amp;市井舞菜@神推偶像登上武道馆我就死而无憾 <br />高咲侑&amp;上原步梦@Love Live! 虹咲学园校园偶像同好会 <br />美树沙耶香&amp;佐仓杏子@魔法少女小圆 <br />玛瑙&amp;时任灯里@处刑少女的生存之道 <br />间宫果乃子&amp;知花纯加@我的百合乃工作是也！ <br />三角初华&amp;丰川祥子@BanG Dream! Ave Mujica <br />缇拉鞠・加德斯布拉德&amp;薇儿赫泽@家里蹲吸血姬的苦闷 <br />春山花奈&amp;薄赖瑞希@群花绽放，彷如修罗 <br />安洁·勒卡雷&amp;公主@公主准则 <br />谏山黄泉&amp;土宫神乐@食灵-零- <br />河合真子&amp;古馆九礼亚@时光流逝，饭菜依旧美味 <br />",
      "first": "0",
      "floor": 92,
      "platform": 0
    },
    {
      "pid": "75489650",
      "author": "thgn5",
      "authorid": "1600030",
      "avatar": "https://i.ibb.co/KDvzLR0/T526.gif",
      "authortitle": "永恒天使",
      "authorgid": "62",
      "author_nickname": "T5",
      "timestamp": "1746256359",
      "subject": "",
      "message": "北条沙都子&amp;古手梨花@寒蝉鸣泣之时 <br />大宫忍&amp;爱丽丝·卡塔雷特@HELLO!! 黄金拼图 <br /><strong><font color=\"White\"><font style=\"background-color:Orange\">保登心爱&amp;香风智乃@请问您今天要来点兔子吗？？</font></font></strong> <br />古宫乃乃香&amp;诺艾尔@天体的秩序 <br />南雫&amp;野田琴音@樱Trick <br />黄前久美子&amp;高坂丽奈@吹响吧！上低音号 第三季 <br />萩生响&amp;江古田莲@ANNE HAPPY♪ <br />千矢&amp;巽绀@Urara迷路帖 <br />凑友希那&amp;今井莉莎@BanG Dream! <br />天堂真矢&amp;西条克洛迪娜@少女☆歌剧 Revue Starlight <br />小糸侑&amp;七海灯子@终将成为你 <br />十仓荣依子&amp;千石冠@Slow Start <br />小邪神&amp;花园百合铃@邪神与厨二病少女 <br />安达樱&amp;岛村抱月@安达与岛村 <br />绘里飘&amp;市井舞菜@神推偶像登上武道馆我就死而无憾 <br />高咲侑&amp;上原步梦@Love Live! 虹咲学园校园偶像同好会 <br />美树沙耶香&amp;佐仓杏子@魔法少女小圆 <br />玛瑙&amp;时任灯里@处刑少女的生存之道 <br />间宫果乃子&amp;知花纯加@我的百合乃工作是也！ <br />三角初华&amp;丰川祥子@BanG Dream! Ave Mujica <br /><strong><font color=\"White\"><font style=\"background-color:Orange\">缇拉鞠・加德斯布拉德&amp;薇儿赫泽@家里蹲吸血姬的苦闷</font></font></strong> <br />春山花奈&amp;薄赖瑞希@群花绽放，彷如修罗 <br />安洁·勒卡雷&amp;公主@公主准则 <br />谏山黄泉&amp;土宫神乐@食灵-零- <br />河合真子&amp;古馆九礼亚@时光流逝，饭菜依旧美味 <br />",
      "first": "0",
      "floor": 93,
      "platform": 0
    },
    {
      "pid": "75489929",
      "author": "HirE",
      "authorid": "2200678",
      "avatar": "https://www.tsdm39.com/uc_server/data/avatar/002/20/06/78_avatar_middle.jpg",
      "authortitle": "水天使",
      "authorgid": "12",
      "author_nickname": "HirE",
      "timestamp": "1746260604",
      "subject": "",
      "message": "北条沙都子&amp;古手梨花@寒蝉鸣泣之时 <br />大宫忍&amp;爱丽丝·卡塔雷特@HELLO!! 黄金拼图 <br />保登心爱&amp;香风智乃@请问您今天要来点兔子吗？？ <br />古宫乃乃香&amp;诺艾尔@天体的秩序 <br />南雫&amp;野田琴音@樱Trick <br />黄前久美子&amp;高坂丽奈@吹响吧！上低音号 第三季 <br />萩生响&amp;江古田莲@ANNE HAPPY♪ <br />千矢&amp;巽绀@Urara迷路帖 <br />凑友希那&amp;今井莉莎@BanG Dream! <br /><strong><font color=\"White\"><font style=\"background-color:Orange\">天堂真矢&amp;西条克洛迪娜@少女☆歌剧 Revue Starlight</font></font></strong> <br /><strong><font color=\"White\"><font style=\"background-color:Orange\">小糸侑&amp;七海灯子@终将成为你</font></font></strong> <br />十仓荣依子&amp;千石冠@Slow Start <br />小邪神&amp;花园百合铃@邪神与厨二病少女 <br /><strong><font color=\"White\"><font style=\"background-color:Orange\">安达樱&amp;岛村抱月@安达与岛村</font></font></strong> <br />绘里飘&amp;市井舞菜@神推偶像登上武道馆我就死而无憾 <br />高咲侑&amp;上原步梦@Love Live! 虹咲学园校园偶像同好会 <br />美树沙耶香&amp;佐仓杏子@魔法少女小圆 <br />玛瑙&amp;时任灯里@处刑少女的生存之道 <br />间宫果乃子&amp;知花纯加@我的百合乃工作是也！ <br />三角初华&amp;丰川祥子@BanG Dream! Ave Mujica <br />缇拉鞠・加德斯布拉德&amp;薇儿赫泽@家里蹲吸血姬的苦闷 <br /><strong><font color=\"White\"><font style=\"background-color:Orange\">春山花奈&amp;薄赖瑞希@群花绽放，彷如修罗</font></font></strong> <br />安洁·勒卡雷&amp;公主@公主准则 <br />谏山黄泉&amp;土宫神乐@食灵-零- <br /><strong><font color=\"White\"><font style=\"background-color:Orange\">河合真子&amp;古馆九礼亚@时光流逝，饭菜依旧美味</font></font></strong> <br />",
      "first": "0",
      "floor": 94,
      "platform": 0
    },
    {
      "pid": "75489946",
      "author": "嘿_小强",
      "authorid": "973949",
      "avatar": "https://i.imgur.com/GpF9nu0.jpg",
      "authortitle": "<font color=\"blue\">梦幻天使</font>",
      "authorgid": "31",
      "author_nickname": "hey~小强",
      "timestamp": "1746260937",
      "subject": "",
      "message": "<strong><font color=\"White\"><font style=\"background-color:Orange\">北条沙都子&amp;古手梨花@寒蝉鸣泣之时</font></font></strong> <br />大宫忍&amp;爱丽丝·卡塔雷特@HELLO!! 黄金拼图 <br />保登心爱&amp;香风智乃@请问您今天要来点兔子吗？？ <br />古宫乃乃香&amp;诺艾尔@天体的秩序 <br />南雫&amp;野田琴音@樱Trick <br /><strong><font color=\"White\"><font style=\"background-color:Orange\">黄前久美子&amp;高坂丽奈@吹响吧！上低音号 第三季</font></font></strong> <br />萩生响&amp;江古田莲@ANNE HAPPY♪ <br />千矢&amp;巽绀@Urara迷路帖 <br />凑友希那&amp;今井莉莎@BanG Dream! <br />天堂真矢&amp;西条克洛迪娜@少女☆歌剧 Revue Starlight <br /><strong><font color=\"White\"><font style=\"background-color:Orange\">小糸侑&amp;七海灯子@终将成为你</font></font></strong> <br />十仓荣依子&amp;千石冠@Slow Start <br />小邪神&amp;花园百合铃@邪神与厨二病少女 <br />安达樱&amp;岛村抱月@安达与岛村 <br />绘里飘&amp;市井舞菜@神推偶像登上武道馆我就死而无憾 <br />高咲侑&amp;上原步梦@Love Live! 虹咲学园校园偶像同好会 <br />美树沙耶香&amp;佐仓杏子@魔法少女小圆 <br />玛瑙&amp;时任灯里@处刑少女的生存之道 <br />间宫果乃子&amp;知花纯加@我的百合乃工作是也！ <br /><strong><font color=\"White\"><font style=\"background-color:Orange\">三角初华&amp;丰川祥子@BanG Dream! Ave Mujica</font></font></strong> <br />缇拉鞠・加德斯布拉德&amp;薇儿赫泽@家里蹲吸血姬的苦闷 <br />春山花奈&amp;薄赖瑞希@群花绽放，彷如修罗 <br /><strong><font color=\"White\"><font style=\"background-color:Orange\">安洁·勒卡雷&amp;公主@公主准则</font></font></strong> <br />谏山黄泉&amp;土宫神乐@食灵-零- <br />河合真子&amp;古馆九礼亚@时光流逝，饭菜依旧美味 <br />",
      "first": "0",
      "floor": 95,
      "platform": 0
    },
    {
      "pid": "75490295",
      "author": "innocentius",
      "authorid": "230447",
      "avatar": "https://p.inari.site/usr/94/67eb7fca7f274.jpg",
      "authortitle": "<font color=\"Red\">版主</font>",
      "authorgid": "3",
      "author_nickname": "",
      "timestamp": "1746265813",
      "subject": "",
      "message": "<strong><font color=\"White\"><font style=\"background-color:Orange\">北条沙都子&amp;古手梨花@寒蝉鸣泣之时</font></font></strong> <br /><strong><font color=\"White\"><font style=\"background-color:Orange\">大宫忍&amp;爱丽丝·卡塔雷特@HELLO!! 黄金拼图</font></font></strong> <br /><strong><font color=\"White\"><font style=\"background-color:Orange\">保登心爱&amp;香风智乃@请问您今天要来点兔子吗？？</font></font></strong> <br />古宫乃乃香&amp;诺艾尔@天体的秩序 <br />南雫&amp;野田琴音@樱Trick <br />黄前久美子&amp;高坂丽奈@吹响吧！上低音号 第三季 <br />萩生响&amp;江古田莲@ANNE HAPPY♪ <br />千矢&amp;巽绀@Urara迷路帖 <br />凑友希那&amp;今井莉莎@BanG Dream! <br />天堂真矢&amp;西条克洛迪娜@少女☆歌剧 Revue Starlight <br />小糸侑&amp;七海灯子@终将成为你 <br />十仓荣依子&amp;千石冠@Slow Start <br /><strong><font color=\"White\"><font style=\"background-color:Orange\">小邪神&amp;花园百合铃@邪神与厨二病少女</font></font></strong> <br />安达樱&amp;岛村抱月@安达与岛村 <br />绘里飘&amp;市井舞菜@神推偶像登上武道馆我就死而无憾 <br />高咲侑&amp;上原步梦@Love Live! 虹咲学园校园偶像同好会 <br />美树沙耶香&amp;佐仓杏子@魔法少女小圆 <br />玛瑙&amp;时任灯里@处刑少女的生存之道 <br />间宫果乃子&amp;知花纯加@我的百合乃工作是也！ <br />三角初华&amp;丰川祥子@BanG Dream! Ave Mujica <br />缇拉鞠・加德斯布拉德&amp;薇儿赫泽@家里蹲吸血姬的苦闷 <br />春山花奈&amp;薄赖瑞希@群花绽放，彷如修罗 <br />安洁·勒卡雷&amp;公主@公主准则 <br />谏山黄泉&amp;土宫神乐@食灵-零- <br />河合真子&amp;古馆九礼亚@时光流逝，饭菜依旧美味 <br />",
      "first": "0",
      "floor": 96,
      "platform": 0
    },
    {
      "pid": "75490658",
      "author": "clenamgr",
      "authorid": "2201692",
      "avatar": "https://www.tsdm39.com/uc_server/data/avatar/002/20/16/92_avatar_middle.jpg",
      "authortitle": "<font color=\"blue\">梦幻天使</font>",
      "authorgid": "31",
      "author_nickname": "Clenamgr",
      "timestamp": "1746269602",
      "subject": "",
      "message": "北条沙都子&amp;古手梨花@寒蝉鸣泣之时 <br />大宫忍&amp;爱丽丝·卡塔雷特@HELLO!! 黄金拼图 <br />保登心爱&amp;香风智乃@请问您今天要来点兔子吗？？ <br />古宫乃乃香&amp;诺艾尔@天体的秩序 <br />南雫&amp;野田琴音@樱Trick <br />黄前久美子&amp;高坂丽奈@吹响吧！上低音号 第三季 <br />萩生响&amp;江古田莲@ANNE HAPPY♪ <br />千矢&amp;巽绀@Urara迷路帖 <br /><strong><font color=\"White\"><font style=\"background-color:Orange\">凑友希那&amp;今井莉莎@BanG Dream!</font></font></strong> <br /><strong><font color=\"White\"><font style=\"background-color:Orange\">天堂真矢&amp;西条克洛迪娜@少女☆歌剧 Revue Starlight</font></font></strong> <br />小糸侑&amp;七海灯子@终将成为你 <br />十仓荣依子&amp;千石冠@Slow Start <br /><strong><font color=\"White\"><font style=\"background-color:Orange\">小邪神&amp;花园百合铃@邪神与厨二病少女</font></font></strong> <br />安达樱&amp;岛村抱月@安达与岛村 <br />绘里飘&amp;市井舞菜@神推偶像登上武道馆我就死而无憾 <br />高咲侑&amp;上原步梦@Love Live! 虹咲学园校园偶像同好会 <br /><strong><font color=\"White\"><font style=\"background-color:Orange\">美树沙耶香&amp;佐仓杏子@魔法少女小圆</font></font></strong> <br />玛瑙&amp;时任灯里@处刑少女的生存之道 <br />间宫果乃子&amp;知花纯加@我的百合乃工作是也！ <br />三角初华&amp;丰川祥子@BanG Dream! Ave Mujica <br />缇拉鞠・加德斯布拉德&amp;薇儿赫泽@家里蹲吸血姬的苦闷 <br />春山花奈&amp;薄赖瑞希@群花绽放，彷如修罗 <br />安洁·勒卡雷&amp;公主@公主准则 <br />谏山黄泉&amp;土宫神乐@食灵-零- <br />河合真子&amp;古馆九礼亚@时光流逝，饭菜依旧美味 <br />",
      "first": "0",
      "floor": 97,
      "platform": 0
    },
    {
      "pid": "75491379",
      "author": "八嘎无路赛",
      "authorid": "2206521",
      "avatar": "https://s2.loli.net/2025/03/09/uSn37X6bUkjNmw4.jpg",
      "authortitle": "<font color=\"blue\">梦幻天使</font>",
      "authorgid": "31",
      "author_nickname": "无梦孤寂",
      "timestamp": "1746277587",
      "subject": "",
      "message": "北条沙都子&amp;古手梨花@寒蝉鸣泣之时 <br />大宫忍&amp;爱丽丝·卡塔雷特@HELLO!! 黄金拼图 <br />保登心爱&amp;香风智乃@请问您今天要来点兔子吗？？ <br />古宫乃乃香&amp;诺艾尔@天体的秩序 <br />南雫&amp;野田琴音@樱Trick <br />黄前久美子&amp;高坂丽奈@吹响吧！上低音号 第三季 <br />萩生响&amp;江古田莲@ANNE HAPPY♪ <br />千矢&amp;巽绀@Urara迷路帖 <br />凑友希那&amp;今井莉莎@BanG Dream! <br />天堂真矢&amp;西条克洛迪娜@少女☆歌剧 Revue Starlight <br /><strong><font color=\"White\"><font style=\"background-color:Orange\">小糸侑&amp;七海灯子@终将成为你</font></font></strong> <br />十仓荣依子&amp;千石冠@Slow Start <br />小邪神&amp;花园百合铃@邪神与厨二病少女 <br />安达樱&amp;岛村抱月@安达与岛村 <br />绘里飘&amp;市井舞菜@神推偶像登上武道馆我就死而无憾 <br />高咲侑&amp;上原步梦@Love Live! 虹咲学园校园偶像同好会 <br />美树沙耶香&amp;佐仓杏子@魔法少女小圆 <br />玛瑙&amp;时任灯里@处刑少女的生存之道 <br />间宫果乃子&amp;知花纯加@我的百合乃工作是也！ <br />三角初华&amp;丰川祥子@BanG Dream! Ave Mujica <br />缇拉鞠・加德斯布拉德&amp;薇儿赫泽@家里蹲吸血姬的苦闷 <br />春山花奈&amp;薄赖瑞希@群花绽放，彷如修罗 <br />安洁·勒卡雷&amp;公主@公主准则 <br />谏山黄泉&amp;土宫神乐@食灵-零- <br />河合真子&amp;古馆九礼亚@时光流逝，饭菜依旧美味 <br />",
      "first": "0",
      "floor": 98,
      "platform": 0
    },
    {
      "pid": "75491722",
      "author": "潮田渚女神",
      "authorid": "1941262",
      "avatar": "http://i.ibb.co/WPb40G5/u-2830386984-3167324828-fm-26-gp-0.jpg",
      "authortitle": "昼天使",
      "authorgid": "13",
      "author_nickname": "渚女神",
      "timestamp": "1746281183",
      "subject": "",
      "message": "北条沙都子&amp;古手梨花@寒蝉鸣泣之时 <br />大宫忍&amp;爱丽丝·卡塔雷特@HELLO!! 黄金拼图 <br /><strong><font color=\"White\"><font style=\"background-color:Orange\">保登心爱&amp;香风智乃@请问您今天要来点兔子吗？？</font></font></strong> <br />古宫乃乃香&amp;诺艾尔@天体的秩序 <br />南雫&amp;野田琴音@樱Trick <br /><strong><font color=\"White\"><font style=\"background-color:Orange\">黄前久美子&amp;高坂丽奈@吹响吧！上低音号 第三季</font></font></strong> <br />萩生响&amp;江古田莲@ANNE HAPPY♪ <br />千矢&amp;巽绀@Urara迷路帖 <br /><strong><font color=\"White\"><font style=\"background-color:Orange\">凑友希那&amp;今井莉莎@BanG Dream!</font></font></strong> <br />天堂真矢&amp;西条克洛迪娜@少女☆歌剧 Revue Starlight <br />小糸侑&amp;七海灯子@终将成为你 <br />十仓荣依子&amp;千石冠@Slow Start <br />小邪神&amp;花园百合铃@邪神与厨二病少女 <br />安达樱&amp;岛村抱月@安达与岛村 <br />绘里飘&amp;市井舞菜@神推偶像登上武道馆我就死而无憾 <br /><strong><font color=\"White\"><font style=\"background-color:Orange\">高咲侑&amp;上原步梦@Love Live! 虹咲学园校园偶像同好会</font></font></strong> <br /><strong><font color=\"White\"><font style=\"background-color:Orange\">美树沙耶香&amp;佐仓杏子@魔法少女小圆</font></font></strong> <br />玛瑙&amp;时任灯里@处刑少女的生存之道 <br />间宫果乃子&amp;知花纯加@我的百合乃工作是也！ <br /><strong><font color=\"White\"><font style=\"background-color:Orange\">三角初华&amp;丰川祥子@BanG Dream! Ave Mujica</font></font></strong> <br />缇拉鞠・加德斯布拉德&amp;薇儿赫泽@家里蹲吸血姬的苦闷 <br />春山花奈&amp;薄赖瑞希@群花绽放，彷如修罗 <br />安洁·勒卡雷&amp;公主@公主准则 <br />谏山黄泉&amp;土宫神乐@食灵-零- <br />河合真子&amp;古馆九礼亚@时光流逝，饭菜依旧美味 <br />",
      "first": "0",
      "floor": 99,
      "platform": 0
    },
    {
      "pid": "75491769",
      "author": "落叶终归根",
      "authorid": "2206790",
      "avatar": "https://tu.ts-dm.net/imgs/2022/06/9efa93f4dde51a94.gif",
      "authortitle": "<font color=\"blue\">梦幻天使</font>",
      "authorgid": "31",
      "author_nickname": "落叶终归根",
      "timestamp": "1746281718",
      "subject": "",
      "message": "北条沙都子&amp;古手梨花@寒蝉鸣泣之时 <br />大宫忍&amp;爱丽丝·卡塔雷特@HELLO!! 黄金拼图 <br /><strong><font color=\"White\"><font style=\"background-color:Orange\">保登心爱&amp;香风智乃@请问您今天要来点兔子吗？？</font></font></strong> <br />古宫乃乃香&amp;诺艾尔@天体的秩序 <br />南雫&amp;野田琴音@樱Trick <br />黄前久美子&amp;高坂丽奈@吹响吧！上低音号 第三季 <br />萩生响&amp;江古田莲@ANNE HAPPY♪ <br />千矢&amp;巽绀@Urara迷路帖 <br />凑友希那&amp;今井莉莎@BanG Dream! <br />天堂真矢&amp;西条克洛迪娜@少女☆歌剧 Revue Starlight <br />小糸侑&amp;七海灯子@终将成为你 <br />十仓荣依子&amp;千石冠@Slow Start <br />小邪神&amp;花园百合铃@邪神与厨二病少女 <br />安达樱&amp;岛村抱月@安达与岛村 <br />绘里飘&amp;市井舞菜@神推偶像登上武道馆我就死而无憾 <br />高咲侑&amp;上原步梦@Love Live! 虹咲学园校园偶像同好会 <br />美树沙耶香&amp;佐仓杏子@魔法少女小圆 <br />玛瑙&amp;时任灯里@处刑少女的生存之道 <br />间宫果乃子&amp;知花纯加@我的百合乃工作是也！ <br />三角初华&amp;丰川祥子@BanG Dream! Ave Mujica <br />缇拉鞠・加德斯布拉德&amp;薇儿赫泽@家里蹲吸血姬的苦闷 <br />春山花奈&amp;薄赖瑞希@群花绽放，彷如修罗 <br />安洁·勒卡雷&amp;公主@公主准则 <br />谏山黄泉&amp;土宫神乐@食灵-零- <br />河合真子&amp;古馆九礼亚@时光流逝，饭菜依旧美味 <br />",
      "first": "0",
      "floor": 100,
      "platform": 0
    }
  ],
  "totalpost": "178",
  "tpp": 10,
  "fid": "418",
  "thread_author": "黑影君",
  "thread_authorid": 1890235,
  "ismoderator": 0,
  "thread_price": "0",
  "thread_paid": 1,
  "extcreditsname": {
    "1": "威望",
    "5": "腹黑",
    "2": "天使币",
    "6": "精灵",
    "7": "金蛋",
    "3": "宣传",
    "4": "天然"
  }
}