{
  "subject": "天使动漫星耀萌战2025——初赛B组",
  "postlist": [
    {
      "pid": "76093888",
      "author": "未梓林",
      "authorid": "1872379",
      "avatar": "https://www.z4a.net/images/2020/07/23/2.gif",
      "authortitle": "<font color=\"Red\">区版主</font>",
      "authorgid": "79",
      "author_nickname": "蠢叽",
      "timestamp": "1753008508",
      "subject": "",
      "message": "高坂桐乃@我的妹妹哪有这么可爱 <br />本间芽衣子@我们仍未知道那天所看见的花的名字 <br />小木曾雪菜@白色相簿2 <br />夏娜@灼眼的夏娜 <br />一之濑琴美@CLANNAD <br /><strong><font color=\"White\"><font style=\"background-color:Orange\">园田海未@LoveLive!</font></font></strong> <br />椎名真白@樱花庄的宠物女孩 <br /><strong><font color=\"White\"><font style=\"background-color:Orange\">泉此方@幸运☆星</font></font></strong> <br />白@NO GAME NO LIFE游戏人生 <br />春日野穹@缘之空 <br />千斗五十铃@甘城光辉游乐园 <br />桂雏菊@旋风管家 <br />见崎鸣@Another <br />壹岐日和@野良神 ARAGOTO <br />长门有希@小长门有希的消失 <br />岁纳京子@摇曳百合3☆Hi! <br />橘万里花@伪恋： <br />忍野忍@物语系列 2nd Season <br />黑羽柚咲@Charlotte <br />久远@传颂之物：虚伪的假面 <br />桂美美@魔法少女伊莉雅3rei! <br />宇佐美瑞希@这个美术部有问题! <br />濑川茜@线上游戏的老婆不可能是女生？ <br />千里朱音@Rewrite <br />玉置亚子@线上游戏的老婆不可能是女生？ <br />久我山八重@少女编号 <br />篝@Rewrite <br />苑生百花@少女编号 <br />",
      "first": "0",
      "floor": 111,
      "platform": 0
    },
    {
      "pid": "76093996",
      "author": "ruik0",
      "authorid": "2029802",
      "avatar": "https://images2.imgbox.com/14/20/7kHE94Fa_o.gif",
      "authortitle": "<font color=\"Red\">萌战组★</font>",
      "authorgid": "142",
      "author_nickname": "r0",
      "timestamp": "1753009969",
      "subject": "",
      "message": "高坂桐乃@我的妹妹哪有这么可爱 <br />本间芽衣子@我们仍未知道那天所看见的花的名字 <br />小木曾雪菜@白色相簿2 <br />夏娜@灼眼的夏娜 <br />一之濑琴美@CLANNAD <br />园田海未@LoveLive! <br />椎名真白@樱花庄的宠物女孩 <br />泉此方@幸运☆星 <br /><strong><font color=\"White\"><font style=\"background-color:Orange\">白@NO GAME NO LIFE游戏人生</font></font></strong> <br />春日野穹@缘之空 <br /><strong><font color=\"White\"><font style=\"background-color:Orange\">千斗五十铃@甘城光辉游乐园</font></font></strong> <br />桂雏菊@旋风管家 <br /><strong><font color=\"White\"><font style=\"background-color:Orange\">见崎鸣@Another</font></font></strong> <br />壹岐日和@野良神 ARAGOTO <br />长门有希@小长门有希的消失 <br />岁纳京子@摇曳百合3☆Hi! <br /><strong><font color=\"White\"><font style=\"background-color:Orange\">橘万里花@伪恋：</font></font></strong> <br /><strong><font color=\"White\"><font style=\"background-color:Orange\">忍野忍@物语系列 2nd Season</font></font></strong> <br />黑羽柚咲@Charlotte <br />久远@传颂之物：虚伪的假面 <br />桂美美@魔法少女伊莉雅3rei! <br /><strong><font color=\"White\"><font style=\"background-color:Orange\">宇佐美瑞希@这个美术部有问题!</font></font></strong> <br />濑川茜@线上游戏的老婆不可能是女生？ <br /><strong><font color=\"White\"><font style=\"background-color:Orange\">千里朱音@Rewrite</font></font></strong> <br />玉置亚子@线上游戏的老婆不可能是女生？ <br />久我山八重@少女编号 <br />篝@Rewrite <br />苑生百花@少女编号 <br />",
      "first": "0",
      "floor": 112,
      "platform": 0
    },
    {
      "pid": "76094147",
      "author": "dodo_123",
      "authorid": "389705",
      "avatar": "https://tu.ts-dm.net/imgs/2025/06/7367187f2a482ada.gif",
      "authortitle": "<font color=\"Red\">漫画组★</font>",
      "authorgid": "111",
      "author_nickname": "",
      "timestamp": "1753012218",
      "subject": "",
      "message": "高坂桐乃@我的妹妹哪有这么可爱 <br />本间芽衣子@我们仍未知道那天所看见的花的名字 <br />小木曾雪菜@白色相簿2 <br /><strong><font color=\"White\"><font style=\"background-color:Orange\">夏娜@灼眼的夏娜</font></font></strong> <br />一之濑琴美@CLANNAD <br />园田海未@LoveLive! <br /><strong><font color=\"White\"><font style=\"background-color:Orange\">椎名真白@樱花庄的宠物女孩</font></font></strong> <br /><strong><font color=\"White\"><font style=\"background-color:Orange\">泉此方@幸运☆星</font></font></strong> <br />白@NO GAME NO LIFE游戏人生 <br />春日野穹@缘之空 <br />千斗五十铃@甘城光辉游乐园 <br />桂雏菊@旋风管家 <br />见崎鸣@Another <br />壹岐日和@野良神 ARAGOTO <br />长门有希@小长门有希的消失 <br />岁纳京子@摇曳百合3☆Hi! <br />橘万里花@伪恋： <br />忍野忍@物语系列 2nd Season <br />黑羽柚咲@Charlotte <br />久远@传颂之物：虚伪的假面 <br />桂美美@魔法少女伊莉雅3rei! <br />宇佐美瑞希@这个美术部有问题! <br />濑川茜@线上游戏的老婆不可能是女生？ <br />千里朱音@Rewrite <br />玉置亚子@线上游戏的老婆不可能是女生？ <br />久我山八重@少女编号 <br />篝@Rewrite <br />苑生百花@少女编号 <br />",
      "first": "0",
      "floor": 113,
      "platform": 0
    }
  ],
  "totalpost": "112",
  "tpp": 10,
  "fid": "418",
  "thread_author": "YQ17",
  "thread_authorid": 1202448,
  "ismoderator": 0,
  "thread_price": "0",
  "thread_paid": 1,
  "extcreditsname": {
    "1": "威望",
    "5": "腹黑",
    "4": "天然",
    "6": "精灵",
    "2": "天使币",
    "3": "宣传",
    "7": "西瓜"
  }
}